{
    "schema":  "ai-local-os-log-manifest-v1",
    "generated_at_utc":  "2026-05-23T13:05:50.4729059Z",
    "generated_at_local":  "2026-05-23T20:05:50.4729059+07:00",
    "share_dir":  "D:\\openwebui\\runtime\\share_logs",
    "latest":  "x112gh_controlled_runtime_binding_full.txt",
    "recent_count":  15,
    "recent":  [
                   {
                       "path":  "x112gh_controlled_runtime_binding_full.txt",
                       "name":  "x112gh_controlled_runtime_binding_full.txt",
                       "kind":  "runtime",
                       "size_bytes":  901,
                       "modified_utc":  "2026-05-23T13:05:50.4050829Z"
                   },
                   {
                       "path":  "x112j_master_review_handoff_contract_full.txt",
                       "name":  "x112j_master_review_handoff_contract_full.txt",
                       "kind":  "log",
                       "size_bytes":  244,
                       "modified_utc":  "2026-05-23T13:05:50.4040835Z"
                   },
                   {
                       "path":  "x112j_master_review_handoff_contract_report.json",
                       "name":  "x112j_master_review_handoff_contract_report.json",
                       "kind":  "log",
                       "size_bytes":  648,
                       "modified_utc":  "2026-05-23T13:05:50.4030731Z"
                   },
                   {
                       "path":  "x112j_master_review_handoff_contract_apply_full.txt",
                       "name":  "x112j_master_review_handoff_contract_apply_full.txt",
                       "kind":  "apply",
                       "size_bytes":  246,
                       "modified_utc":  "2026-05-23T13:05:50.4013812Z"
                   },
                   {
                       "path":  "x112j_x103_lines_35_105.txt",
                       "name":  "x112j_x103_lines_35_105.txt",
                       "kind":  "log",
                       "size_bytes":  1729,
                       "modified_utc":  "2026-05-23T13:05:50.4002386Z"
                   },
                   {
                       "path":  "x112i_class_method_adapter_binding_report.json",
                       "name":  "x112i_class_method_adapter_binding_report.json",
                       "kind":  "log",
                       "size_bytes":  50594,
                       "modified_utc":  "2026-05-23T13:05:50.3984668Z"
                   },
                   {
                       "path":  "x112i_class_method_adapter_binding_full.txt",
                       "name":  "x112i_class_method_adapter_binding_full.txt",
                       "kind":  "log",
                       "size_bytes":  432,
                       "modified_utc":  "2026-05-23T13:05:50.3955043Z"
                   },
                   {
                       "path":  "x112j_verify_after_fix_full.txt",
                       "name":  "x112j_verify_after_fix_full.txt",
                       "kind":  "log",
                       "size_bytes":  434,
                       "modified_utc":  "2026-05-23T13:05:50.3937530Z"
                   },
                   {
                       "path":  "x112j_live_latest_reports.txt",
                       "name":  "x112j_live_latest_reports.txt",
                       "kind":  "runtime",
                       "size_bytes":  1777,
                       "modified_utc":  "2026-05-23T13:05:50.3926587Z"
                   },
                   {
                       "path":  "x112_registry_cache_dump.txt",
                       "name":  "x112_registry_cache_dump.txt",
                       "kind":  "log",
                       "size_bytes":  43948,
                       "modified_utc":  "2026-05-23T13:05:36.7757877Z"
                   },
                   {
                       "path":  "x112_dispatcher_adapter_probe.txt",
                       "name":  "x112_dispatcher_adapter_probe.txt",
                       "kind":  "log",
                       "size_bytes":  349,
                       "modified_utc":  "2026-05-23T13:05:36.7725934Z"
                   },
                   {
                       "path":  "x112b_dispatcher_adapter_resolver.txt",
                       "name":  "x112b_dispatcher_adapter_resolver.txt",
                       "kind":  "log",
                       "size_bytes":  5,
                       "modified_utc":  "2026-05-23T13:05:36.7715415Z"
                   },
                   {
                       "path":  "x112b_dispatcher_adapter_resolver_full.txt",
                       "name":  "x112b_dispatcher_adapter_resolver_full.txt",
                       "kind":  "log",
                       "size_bytes":  532,
                       "modified_utc":  "2026-05-23T13:05:36.7699900Z"
                   },
                   {
                       "path":  "x112b2_dispatcher_adapter_resolver_report.json",
                       "name":  "x112b2_dispatcher_adapter_resolver_report.json",
                       "kind":  "log",
                       "size_bytes":  1130,
                       "modified_utc":  "2026-05-23T13:05:36.7684266Z"
                   },
                   {
                       "path":  "x112b2_dispatcher_adapter_resolver_report.txt",
                       "name":  "x112b2_dispatcher_adapter_resolver_report.txt",
                       "kind":  "log",
                       "size_bytes":  386,
                       "modified_utc":  "2026-05-23T13:05:36.7672267Z"
                   }
               ],
    "raw_base":  "https://raw.githubusercontent.com/haclongdd/share-logs/main/"
}
